nimfa/__init__.py
nimfa/version.py
nimfa/datasets/__init__.py
nimfa/datasets/__init__.pyc
nimfa/datasets/ALL_AML/ALL_AML_data.txt
nimfa/datasets/ALL_AML/ALL_AML_genes.txt
nimfa/datasets/ALL_AML/ALL_AML_samples.txt
nimfa/datasets/CBCL_faces/README.md
nimfa/datasets/Medlars/README.md
nimfa/datasets/Medulloblastoma/Medulloblastoma_data.txt
nimfa/datasets/Medulloblastoma/Medulloblastoma_genes.txt
nimfa/datasets/Medulloblastoma/Medulloblastomas_samples.txt
nimfa/datasets/MovieLens/README.md
nimfa/datasets/ORL_faces/s1/1.pgm
nimfa/datasets/ORL_faces/s1/10.pgm
nimfa/datasets/ORL_faces/s1/2.pgm
nimfa/datasets/ORL_faces/s1/3.pgm
nimfa/datasets/ORL_faces/s1/4.pgm
nimfa/datasets/ORL_faces/s1/5.pgm
nimfa/datasets/ORL_faces/s1/6.pgm
nimfa/datasets/ORL_faces/s1/7.pgm
nimfa/datasets/ORL_faces/s1/8.pgm
nimfa/datasets/ORL_faces/s1/9.pgm
nimfa/datasets/ORL_faces/s10/1.pgm
nimfa/datasets/ORL_faces/s10/10.pgm
nimfa/datasets/ORL_faces/s10/2.pgm
nimfa/datasets/ORL_faces/s10/3.pgm
nimfa/datasets/ORL_faces/s10/4.pgm
nimfa/datasets/ORL_faces/s10/5.pgm
nimfa/datasets/ORL_faces/s10/6.pgm
nimfa/datasets/ORL_faces/s10/7.pgm
nimfa/datasets/ORL_faces/s10/8.pgm
nimfa/datasets/ORL_faces/s10/9.pgm
nimfa/datasets/ORL_faces/s10/target.jpg
nimfa/datasets/ORL_faces/s11/1.pgm
nimfa/datasets/ORL_faces/s11/10.pgm
nimfa/datasets/ORL_faces/s11/2.pgm
nimfa/datasets/ORL_faces/s11/3.pgm
nimfa/datasets/ORL_faces/s11/4.pgm
nimfa/datasets/ORL_faces/s11/5.pgm
nimfa/datasets/ORL_faces/s11/6.pgm
nimfa/datasets/ORL_faces/s11/7.pgm
nimfa/datasets/ORL_faces/s11/8.pgm
nimfa/datasets/ORL_faces/s11/9.pgm
nimfa/datasets/ORL_faces/s12/1.pgm
nimfa/datasets/ORL_faces/s12/10.pgm
nimfa/datasets/ORL_faces/s12/2.pgm
nimfa/datasets/ORL_faces/s12/3.pgm
nimfa/datasets/ORL_faces/s12/4.pgm
nimfa/datasets/ORL_faces/s12/5.pgm
nimfa/datasets/ORL_faces/s12/6.pgm
nimfa/datasets/ORL_faces/s12/7.pgm
nimfa/datasets/ORL_faces/s12/8.pgm
nimfa/datasets/ORL_faces/s12/9.pgm
nimfa/datasets/ORL_faces/s13/1.pgm
nimfa/datasets/ORL_faces/s13/10.pgm
nimfa-1.4.0.dist-info/AUTHORS.md
nimfa-1.4.0.dist-info/COPYING.txt
nimfa-1.4.0.dist-info/METADATA
nimfa-1.4.0.dist-info/WHEEL
nimfa-1.4.0.dist-info/top_level.txt
nimfa-1.4.0.dist-info/RECORD
