Metadata-Version: 2.1
Name: nimfa
Version: 1.4.0
Summary: A Python module for nonnegative matrix factorization
Home-page: http://nimfa.biolab.si
Author: Marinka Zitnik
Author-email: marinka@cs.stanford.edu
Maintainer: Marinka Zitnik
Maintainer-email: marinka@cs.stanford.edu
License: BSD
Download-URL: http://github.com/marinkaz/nimfa
Keywords: matrix factorization,nonnegative matrix factorization,bioinformatics,data mining,machine learning
Platform: UNKNOWN
Classifier: Intended Audience :: Science/Research
Classifier: Intended Audience :: Developers
Classifier: License :: OSI Approved
Classifier: Programming Language :: Python
Classifier: Topic :: Software Development
Classifier: Topic :: Scientific/Engineering
Classifier: Topic :: Scientific/Engineering :: Artificial Intelligence
Classifier: Topic :: Scientific/Engineering :: Bio-Informatics
Classifier: Programming Language :: Python :: 2
Classifier: Programming Language :: Python :: 3
